flask_redisddaxg/__init__.py
flask_redisosgearth/__init__.py
flask_redisosgearth-0.0.2.dist-info/METADATA
flask_redisosgearth-0.0.2.dist-info/RECORD
flask_redisosgearth-0.0.2.dist-info/WHEEL
flask_redisosgearth-0.0.2.dist-info/top_level.txt
