Metadata-Version: 2.1
Name: flask-redisosgearth
Version: 0.0.2
Summary: Flask extension for redis
Home-page: UNKNOWN
Author: duoduoaixiaogai
Author-email: 490850477@qq.com
Maintainer: duoduoaixiaogai
Maintainer-email: 490850477@qq.com
License: BSD
Platform: any
Classifier: Environment :: Web Environment
Classifier: Intended Audience :: Developers
Classifier: License :: OSI Approved :: BSD License
Classifier: Operating System :: OS Independent
Classifier: Programming Language :: Python
Classifier: Topic :: Internet :: WWW/HTTP :: Dynamic Content
Classifier: Topic :: Software Development :: Libraries :: Python Modules
